brainchop/__init__.py
brainchop/api.py
brainchop/cli.py
brainchop/convert_tfjs_to_pth.py
brainchop/export_model.py
brainchop/tiny_meshnet.py
brainchop/utils.py
brainchop/niimath/__init__.py
brainchop-0.2.dist-info/licenses/LICENSE
brainchop-0.2.dist-info/METADATA
brainchop-0.2.dist-info/WHEEL
brainchop-0.2.dist-info/entry_points.txt
brainchop-0.2.dist-info/top_level.txt
brainchop-0.2.dist-info/RECORD
