Metadata-Version: 2.4
Name: brainchop
Version: 0.2
Summary: Portable and lightweight brain segmentation using tinygrad
Author-email: Mike Doan <spikedoanz@gmail.com>
License: MIT
Project-URL: Homepage, https://github.com/neuroneural/brainchop-cli
Project-URL: Repository, https://github.com/neuroneural/brainchop-cli
Classifier: Programming Language :: Python :: 3
Classifier: License :: OSI Approved :: MIT License
Classifier: Operating System :: OS Independent
Requires-Python: >=3.10
License-File: LICENSE
Requires-Dist: numpy
Requires-Dist: tinygrad
Requires-Dist: niimath>=1.0.20250804
Requires-Dist: requests
Requires-Dist: safetensors
Provides-Extra: all
Requires-Dist: mkdocs; extra == "all"
Requires-Dist: mkdocs-material; extra == "all"
Requires-Dist: mkdocstrings[python]; extra == "all"
Requires-Dist: pytest; extra == "all"
Requires-Dist: ruff; extra == "all"
Dynamic: license-file
